{
  "LM04": {
    "jp": "チェン",
    "en": "Ch'en",
    "ch": "陈"
  },
  "GG01": {
    "jp": "シージ",
    "en": "Siege",
    "ch": "推进之王"
  },
  "FO01": {
    "jp": "シャイニング",
    "en": "Shining",
    "ch": "闪灵"
  },
  "FO03": {
    "jp": "ナイチンゲール",
    "en": "Nightingale",
    "ch": "夜莺"
  },
  "RL03": {
    "jp": "イフリータ",
    "en": "Ifrit",
    "ch": "伊芙利特"
  },
  "LN02": {
    "jp": "エイヤフィヤトラ",
    "en": "Eyjafjalla",
    "ch": "艾雅法拉"
  },
  "PL03": {
    "jp": "エクシア",
    "en": "Exusiai",
    "ch": "能天使"
  },
  "SR02": {
    "jp": "アンジェリーナ",
    "en": "Angelina",
    "ch": "安洁莉娜"
  },
  "JC01": {
    "jp": "シルバーアッシュ",
    "en": "SilverAsh",
    "ch": "银灰"
  },
  "LM05": {
    "jp": "ホシグマ",
    "en": "Hoshiguma",
    "ch": "星熊"
  },
  "RL02": {
    "jp": "サリア",
    "en": "Saria",
    "ch": "塞雷娅"
  },
  "AA01": {
    "jp": "スカジ",
    "en": "Skadi",
    "ch": "斯卡蒂"
  },
  "SS02": {
    "jp": "シュヴァルツ",
    "en": "Schwarz",
    "ch": "黑"
  },
  "AZ01": {
    "jp": "ヘラグ",
    "en": "Hellagur",
    "ch": "赫拉格"
  },
  "RL06": {
    "jp": "マゼラン",
    "en": "Magallan",
    "ch": "麦哲伦"
  },
  "LT77": {
    "jp": "モスティマ",
    "en": "Mostima",
    "ch": "莫斯提马"
  },
  "RE41": {
    "jp": "ブレイズ",
    "en": "Blaze",
    "ch": "煌"
  },
  "LM20": {
    "jp": "ア",
    "en": "Aak",
    "ch": "阿"
  },
  "NM01": {
    "jp": "ニェン",
    "en": "Nian",
    "ch": "年"
  },
  "R155": {
    "jp": "ケオベ",
    "en": "Ceobe",
    "ch": "刻俄柏"
  },
  "RV02": {
    "jp": "バグパイプ",
    "en": "Bagpipe",
    "ch": "风笛"
  },
  "R109": {
    "jp": "ファントム",
    "en": "Phantom",
    "ch": "傀影"
  },
  "B214": {
    "jp": "W",
    "en": "W",
    "ch": "W"
  },
  "R117": {
    "jp": "ウィーディ",
    "en": "Weedy",
    "ch": "温蒂"
  },
  "USS4": {
    "jp": "ロサ",
    "en": "Rosa",
    "ch": "早露"
  },
  "R172": {
    "jp": "スズラン",
    "en": "Suzuran",
    "ch": "铃兰"
  },
  "II01": {
    "jp": "ソーンズ",
    "en": "Thorns",
    "ch": "棘刺"
  },
  "SG03": {
    "jp": "ユーネクテス",
    "en": "Eunectes",
    "ch": "森蚺"
  },
  "R111": {
    "jp": "スルト",
    "en": "Surtr",
    "ch": "史尔特尔"
  },
  "KZ09": {
    "jp": "ブレミシャイン",
    "en": "Blemishine",
    "ch": "瑕光"
  },
  "RE45": {
    "jp": "ロスモンティス",
    "en": "Rosmontis",
    "ch": "迷迭香"
  },
  "R159": {
    "jp": "マドロック",
    "en": "Mudrock",
    "ch": "泥岩"
  },
  "CB05": {
    "jp": "マウンテン",
    "en": "Mountain",
    "ch": "山"
  },
  "LT08": {
    "jp": "アルケット",
    "en": "Archetto",
    "ch": "空弦"
  },
  "NM02": {
    "jp": "シー",
    "en": "Dusk",
    "ch": "夕"
  },
  "HK13": {
    "jp": "サガ",
    "en": "Saga",
    "ch": "嵯峨"
  },
  "RS01": {
    "jp": "Ash",
    "en": "Ash",
    "ch": "灰烬"
  },
  "SG07": {
    "jp": "パッセンジャー",
    "en": "Passenger",
    "ch": "异客"
  },
  "CR01": {
    "jp": "濁心スカジ",
    "en": "Skadi C.H.",
    "ch": "浊心斯卡蒂"
  },
  "B003": {
    "jp": "ケルシー",
    "en": "kal'tsit",
    "ch": "凯尔希"
  },
  "AA05": {
    "jp": "グレイディーア",
    "en": "Gladiia",
    "ch": "歌蕾蒂娅"
  },
  "LN04": {
    "jp": "カーネリアン",
    "en": "Carnelian",
    "ch": "卡涅利安"
  },
  "MN04": {
    "jp": "パラス",
    "en": "Pallas",
    "ch": "帕拉斯"
  },
  "R112": {
    "jp": "遊龍チェン",
    "en": "Ch'en H.D.",
    "ch": "假日威龙陈"
  },
  "HK07": {
    "jp": "ミヅキ",
    "en": "Mizuki",
    "ch": "水月"
  },
  "VC10": {
    "jp": "サイラッハ",
    "en": "Saileach",
    "ch": "琴柳"
  },
  "KZ13": {
    "jp": "ファートゥース",
    "en": "Fartooth",
    "ch": "远牙"
  },
  "KZ01": {
    "jp": "耀騎士ニアール",
    "en": "Nearl R.K.",
    "ch": "耀骑士临光"
  },
  "KZ11": {
    "jp": "フレイムテイル",
    "en": "Flametail",
    "ch": "焰尾"
  },
  "JC02": {
    "jp": "ノーシス",
    "en": "Gnosis",
    "ch": "灵知"
  },
  "NM03": {
    "jp": "リィン",
    "en": "Ling",
    "ch": "令"
  },
  "LM18": {
    "jp": "リー",
    "en": "Lee",
    "ch": "老鲤"
  },
  "VC09": {
    "jp": "ゴールデングロー",
    "en": "Goldenglow",
    "ch": "澄闪"
  },
  "LT11": {
    "jp": "フィアメッタ",
    "en": "Fiammetta",
    "ch": "菲亚梅塔"
  },
  "VC16": {
    "jp": "ホルン",
    "en": "Horn",
    "ch": "号角"
  },
  "II07": {
    "jp": "アイリーニ",
    "en": "Irene",
    "ch": "艾丽妮"
  },
  "CR02": {
    "jp": "帰溟スペクター",
    "en": "Specter U.C.",
    "ch": "归溟幽灵鲨"
  },
  "II09": {
    "jp": "ルーメン",
    "en": "Lumen",
    "ch": "流明"
  },
  "LN05": {
    "jp": "エーベンホルツ",
    "en": "Ebenholz",
    "ch": "黑键"
  },
  "RL07": {
    "jp": "ドロシー",
    "en": "Dorothy",
    "ch": "多萝西"
  },
  "RF22": {
    "jp": "百錬ガヴィル",
    "en": "Gavial I.V.",
    "ch": "百炼嘉维尔"
  },
  "R145": {
    "jp": "パゼオンカ",
    "en": "Pozemka",
    "ch": "鸿雪"
  },
  "KZ08": {
    "jp": "ムリナール",
    "en": "Mlynar",
    "ch": "玛恩纳"
  },
  "VC17": {
    "jp": "ステインレス",
    "en": "Stainless",
    "ch": "白铁"
  },
  "PL07": {
    "jp": "血掟テキサス",
    "en": "Texas T.O.",
    "ch": "缄默德克萨斯"
  },
  "SR35": {
    "jp": "ペナンス",
    "en": "Penance",
    "ch": "斥罪"
  },
  "SR36": {
    "jp": "ヴィジェル",
    "en": "Vigil",
    "ch": "伺夜"
  },
  "DB02": {
    "jp": "焰影リード",
    "en": "Reed F.S.",
    "ch": "焰影苇草"
  },
  "NM04": {
    "jp": "チョンユエ",
    "en": "Chongyue",
    "ch": "重岳"
  },
  "LM21": {
    "jp": "リン",
    "en": "Lin",
    "ch": "林"
  },
  "YD20": {
    "jp": "チューバイ",
    "en": "Qiu Bai",
    "ch": "仇白"
  },
  "MH02": {
    "jp": "キリンRヤトウ",
    "en": "Yato K.R",
    "ch": "麒麟R夜刀"
  },
  "B215": {
    "jp": "イネス",
    "en": "Ines",
    "ch": "伊内丝"
  },
  "RL09": {
    "jp": "ミュルジス",
    "en": "Muelsyse",
    "ch": "缪尔赛思"
  },
  "CB88": {
    "jp": "ホルハイヤ",
    "en": "Ho’olheyak",
    "ch": "霍尔海雅"
  },
  "RL10": {
    "jp": "淬羽サイレンス",
    "en": "Silence T.P.",
    "ch": "淬羽赫默"
  },
  "LT40": {
    "jp": "聖約イグゼキュター",
    "en": "Executor E.F.",
    "ch": "圣约送葬人"
  },
  "SI07": {
    "jp": "ティフォン",
    "en": "Typhon",
    "ch": "提丰"
  },
  "LN10": {
    "jp": "純燼エイヤフィヤトラ",
    "en": "Eyjafjalla H.A.",
    "ch": "纯烬艾雅法拉"
  },
  "LM22": {
    "jp": "琳琅スワイヤー",
    "en": "Swire E.W.",
    "ch": "琳琅诗怀雅"
  },
  "BS30": {
    "jp": "滌火ジェシカ",
    "en": "Jessica T.L.",
    "ch": "涤火杰西卡"
  },
  "B216": {
    "jp": "ヘドリー",
    "en": "Hoederer",
    "ch": "赫德雷"
  },
  "LT22": {
    "jp": "ヴィルトゥオーサ",
    "en": "Virtuosa",
    "ch": "塑心"
  },
  "LN11": {
    "jp": "ヴィヴィアナ",
    "en": "Viviana",
    "ch": "薇薇安娜"
  },
  "LN07": {
    "jp": "レッシング",
    "en": "Lessing",
    "ch": "止颂"
  },
  "JC07": {
    "jp": "デーゲンブレヒャー",
    "en": "Degenbrecher",
    "ch": "锏"
  },
  "RB15": {
    "jp": "レイ",
    "en": "Ray",
    "ch": "莱伊"
  },
  "NM05": {
    "jp": "シュウ",
    "en": "Shu",
    "ch": "黍"
  },
  "YD06": {
    "jp": "ズオ・ラウ",
    "en": "Zuo Le",
    "ch": "左乐"
  },
  "RS05": {
    "jp": "Ela",
    "en": "Ela",
    "ch": "艾拉"
  },
  "SW00": {
    "jp": "アスカロン",
    "en": "Ascalon",
    "ch": "阿斯卡纶"
  },
  "B00W": {
    "jp": "ウィシャデル",
    "en": "Wiš’adel",
    "ch": "维什戴尔"
  },
  "RE03": {
    "jp": "ロゴス",
    "en": "Logos",
    "ch": "逻各斯"
  },
  "DWDB": {
    "jp": "シヴィライト・エテルナ",
    "en": "Civilight Eterna",
    "ch": "魔王"
  },
  "AA00": {
    "jp": "ウルピアヌス",
    "en": "Ulpianus",
    "ch": "乌尔比安"
  },
  "R182": {
    "jp": "ニンフ",
    "en": "Nymph",
    "ch": "妮芙"
  },
  "SG14": {
    "jp": "ペペ",
    "en": "Pepe",
    "ch": "佩佩"
  },
  "SG17": {
    "jp": "ナラントゥヤ",
    "en": "Narantuya",
    "ch": "娜仁图亚"
  },
  "DD02": {
    "jp": "マルシル",
    "en": "Marcile",
    "ch": "玛露西尔"
  },
  "VC00": {
    "jp": "ヴィーナ・ヴィクトリア",
    "en": "Vina Victoria",
    "ch": "维娜・维多利亚"
  },
  "SR04": {
    "jp": "荒廃ラップランド",
    "en": "Lappland T.D.",
    "ch": "荒芜拉普兰德"
  },
  "SR40": {
    "jp": "ヴァルピスフォーリア",
    "en": "Vulpisfoglia",
    "ch": "忍冬"
  },
  "R315": {
    "jp": "クラウンスレイヤー",
    "en": "CrownSlayer",
    "ch": "弑君者"
  },
  "II02": {
    "jp": "引星ソーンズ",
    "en": "Thorns T.L.",
    "ch": "引星棘刺"
  },
  "NM06": {
    "jp": "ユウ",
    "en": "Yu",
    "ch": "余"
  },
  "REX1": {
    "jp": "ジュウホァン",
    "en": "Blaze I.S.",
    "ch": "烛煌"
  },
  "R169": {
    "jp": "エンテレケイア",
    "en": "Entelechia",
    "ch": "隐德来希"
  },
  "RB01": {
    "jp": "サベージ",
    "en": "Savage",
    "ch": "暴行"
  },
  "PL02": {
    "jp": "テキサス",
    "en": "Texas",
    "ch": "德克萨斯"
  },
  "USS1": {
    "jp": "ズィマー",
    "en": "Zima",
    "ch": "凛冬"
  },
  "RL04": {
    "jp": "フィリオプシス",
    "en": "Ptilopsis",
    "ch": "白面鸮"
  },
  "RL01": {
    "jp": "サイレンス",
    "en": "Silence",
    "ch": "赫默"
  },
  "R106": {
    "jp": "ワルファリン",
    "en": "Warfarin",
    "ch": "华法琳"
  },
  "R001": {
    "jp": "アーミヤ",
    "en": "Amiya",
    "ch": "阿米娅"
  },
  "R001_2": {
    "jp": "昇格アーミヤ(前衛)",
    "en": "Amiya Alter",
    "ch": "阿米娅(近卫)"
  },
  "R001_3": {
    "jp": "昇格アーミヤ(医療)",
    "en": "Amiya Alter",
    "ch": "阿米娅(医疗)"
  },
  "VC03": {
    "jp": "ナイトメア",
    "en": "Nightmare",
    "ch": "夜魔"
  },
  "SK01": {
    "jp": "スカイフレア",
    "en": "Skyfire",
    "ch": "天火"
  },
  "SW01": {
    "jp": "レッド",
    "en": "Projekt Red",
    "ch": "红"
  },
  "SG01": {
    "jp": "マンティコア",
    "en": "Manticore",
    "ch": "狮蝎"
  },
  "JC06": {
    "jp": "クリフハート",
    "en": "Cliffheart",
    "ch": "崖心"
  },
  "YD01": {
    "jp": "エフイーター",
    "en": "FEater",
    "ch": "食铁兽"
  },
  "SR03": {
    "jp": "プロヴァンス",
    "en": "Provence",
    "ch": "普罗旺斯"
  },
  "AA03": {
    "jp": "アズリウス",
    "en": "Blue Poison",
    "ch": "蓝毒"
  },
  "ST01": {
    "jp": "ファイヤーウォッチ",
    "en": "Firewatch",
    "ch": "守林人"
  },
  "ST03": {
    "jp": "メテオリーテ",
    "en": "Meteorite",
    "ch": "陨星"
  },
  "KZ03": {
    "jp": "プラチナ",
    "en": "Platinum",
    "ch": "白金"
  },
  "JC05": {
    "jp": "プラマニクス",
    "en": "Pramanix",
    "ch": "初雪"
  },
  "USS2": {
    "jp": "イースチナ",
    "en": "Istina",
    "ch": "真理"
  },
  "RL05": {
    "jp": "メイヤー",
    "en": "Mayer",
    "ch": "梅尔"
  },
  "PL05": {
    "jp": "ソラ",
    "en": "Sora",
    "ch": "空"
  },
  "BS01": {
    "jp": "フランカ",
    "en": "Franka",
    "ch": "芙兰卡"
  },
  "AA02": {
    "jp": "スペクター",
    "en": "Specter",
    "ch": "幽灵鲨"
  },
  "GG03": {
    "jp": "インドラ",
    "en": "Indra",
    "ch": "因陀罗"
  },
  "SR01": {
    "jp": "ラップランド",
    "en": "Lappland",
    "ch": "拉普兰德"
  },
  "FO02": {
    "jp": "ニアール",
    "en": "Nearl",
    "ch": "临光"
  },
  "BS02": {
    "jp": "リスカム",
    "en": "Liskarm",
    "ch": "雷蛇"
  },
  "MN02": {
    "jp": "ヴァルカン",
    "en": "Vulcan",
    "ch": "火神"
  },
  "PL04": {
    "jp": "クロワッサン",
    "en": "Croissant",
    "ch": "可颂"
  },
  "VC05": {
    "jp": "グラニ",
    "en": "Grani",
    "ch": "格拉尼"
  },
  "LM08": {
    "jp": "スワイヤー",
    "en": "Swire",
    "ch": "诗怀雅"
  },
  "R128": {
    "jp": "グラウコス",
    "en": "Glaucus",
    "ch": "格劳克斯"
  },
  "SS01": {
    "jp": "セイロン",
    "en": "Ceylon",
    "ch": "锡兰"
  },
  "RR01": {
    "jp": "アステシア",
    "en": "Astesia",
    "ch": "星极"
  },
  "R137": {
    "jp": "エンカク",
    "en": "Flamebringer",
    "ch": "炎客"
  },
  "LT01": {
    "jp": "イグゼキュター",
    "en": "Executor",
    "ch": "送葬人"
  },
  "R132": {
    "jp": "ブリーズ",
    "en": "Breeze",
    "ch": "微风"
  },
  "LM12": {
    "jp": "ワイフー",
    "en": "Waai Fu",
    "ch": "槐琥"
  },
  "LM15": {
    "jp": "バイソン",
    "en": "Bison",
    "ch": "拜松"
  },
  "HT03": {
    "jp": "リード",
    "en": "Reed",
    "ch": "苇草"
  },
  "SR27": {
    "jp": "ブローカ",
    "en": "Broca",
    "ch": "布洛卡"
  },
  "R110": {
    "jp": "グレースロート",
    "en": "GreyThroat",
    "ch": "灰喉"
  },
  "LM16": {
    "jp": "スノーズント",
    "en": "Snowsant",
    "ch": "雪雉"
  },
  "LM19": {
    "jp": "ウン",
    "en": "Hung",
    "ch": "吽"
  },
  "YD05": {
    "jp": "レイズ",
    "en": "Leizi",
    "ch": "惊蛰"
  },
  "R138": {
    "jp": "バイビーク",
    "en": "Bibeak",
    "ch": "柏喙"
  },
  "R158": {
    "jp": "シェーシャ",
    "en": "Sesa",
    "ch": "慑砂"
  },
  "R148": {
    "jp": "シャマレ",
    "en": "Shamare",
    "ch": "巫恋"
  },
  "R126": {
    "jp": "シデロカ",
    "en": "Sideroca",
    "ch": "铸铁"
  },
  "R131": {
    "jp": "エリジウム",
    "en": "Elysium",
    "ch": "极境"
  },
  "RB05": {
    "jp": "アスベストス",
    "en": "Asbestos",
    "ch": "石棉"
  },
  "R129": {
    "jp": "ツキノギ",
    "en": "Tsukinogi",
    "ch": "月禾"
  },
  "US11": {
    "jp": "アブサント",
    "en": "Absinthe",
    "ch": "苦艾"
  },
  "RB03": {
    "jp": "レオンハルト",
    "en": "Leonhardt",
    "ch": "莱恩哈特"
  },
  "RB04": {
    "jp": "エアースカーペ",
    "en": "Ayerscarpe",
    "ch": "断崖"
  },
  "R133": {
    "jp": "フォリニック",
    "en": "Folinic",
    "ch": "亚叶"
  },
  "R147": {
    "jp": "ビーズワクス",
    "en": "Beeswax",
    "ch": "蜜蜡"
  },
  "SR26": {
    "jp": "キアーベ",
    "en": "Chiave",
    "ch": "贾维"
  },
  "R162": {
    "jp": "シーン",
    "en": "Scene",
    "ch": "稀音"
  },
  "II04": {
    "jp": "アンドレアナ",
    "en": "Andreana",
    "ch": "安哲拉"
  },
  "SG05": {
    "jp": "トミミ",
    "en": "Tomimi",
    "ch": "特米米"
  },
  "SG06": {
    "jp": "フリント",
    "en": "Flint",
    "ch": "燧石"
  },
  "VC08": {
    "jp": "ミント",
    "en": "Mint",
    "ch": "薄绿"
  },
  "RB07": {
    "jp": "エイプリル",
    "en": "April",
    "ch": "四月"
  },
  "SR28": {
    "jp": "アオスタ",
    "en": "Aosta",
    "ch": "奥斯塔"
  },
  "KZ07": {
    "jp": "ウィスラッシュ",
    "en": "Whislash",
    "ch": "鞭刃"
  },
  "R163": {
    "jp": "ウィスパーレイン",
    "en": "Whisperain",
    "ch": "絮雨"
  },
  "CB06": {
    "jp": "カフカ",
    "en": "Kafka",
    "ch": "卡夫卡"
  },
  "CB08": {
    "jp": "ロビン",
    "en": "Robin",
    "ch": "罗宾"
  },
  "VC12": {
    "jp": "アイリス",
    "en": "Iris",
    "ch": "爱丽丝"
  },
  "SG08": {
    "jp": "トゥイェ",
    "en": "Tuye",
    "ch": "图耶"
  },
  "RF01": {
    "jp": "炎獄ラヴァ",
    "en": "Purgatory",
    "ch": "炎狱炎熔"
  },
  "YD11": {
    "jp": "ウユウ",
    "en": "Mr.Nothing",
    "ch": "乌有"
  },
  "RS03": {
    "jp": "Frost",
    "en": "Frost",
    "ch": "霜华"
  },
  "RS02": {
    "jp": "Blitz",
    "en": "Blitz",
    "ch": "闪击"
  },
  "RS04": {
    "jp": "Tachanka",
    "en": "Tachanka",
    "ch": "战车"
  },
  "VC11": {
    "jp": "トギフォンス",
    "en": "Toddifons",
    "ch": "熔泉"
  },
  "R164": {
    "jp": "ヘビーレイン",
    "en": "Heavyrain",
    "ch": "暴雨"
  },
  "HK04": {
    "jp": "アカフユ",
    "en": "Akafuyu",
    "ch": "赤冬"
  },
  "HK05": {
    "jp": "キララ",
    "en": "Kirara",
    "ch": "绮良"
  },
  "VC14": {
    "jp": "ベナ",
    "en": "Bena",
    "ch": "贝娜"
  },
  "BV13": {
    "jp": "ラ・プルマ",
    "en": "La Pluma",
    "ch": "羽毛笔"
  },
  "BV12": {
    "jp": "テキーラ",
    "en": "Tequila",
    "ch": "龙舌兰"
  },
  "YD03": {
    "jp": "マルベリー",
    "en": "Mulberry",
    "ch": "桑葚"
  },
  "KZ12": {
    "jp": "アッシュロック",
    "en": "Ashlock",
    "ch": "灰毫"
  },
  "CB12": {
    "jp": "コロセラム",
    "en": "Corroserum",
    "ch": "蚀清"
  },
  "RB06": {
    "jp": "ハニーベリー",
    "en": "Honeyberry",
    "ch": "蜜莓"
  },
  "KZ14": {
    "jp": "ワイルドメイン",
    "en": "Wild Mane",
    "ch": "野鬃"
  },
  "JC09": {
    "jp": "オーロラ",
    "en": "Aurora",
    "ch": "极光"
  },
  "JC00": {
    "jp": "イェラ",
    "en": "Kjera",
    "ch": "耶拉"
  },
  "VC07": {
    "jp": "シャレム",
    "en": "Shalem",
    "ch": "暮落"
  },
  "YD09": {
    "jp": "クシキロク",
    "en": "9-Colored Deer",
    "ch": "九色鹿"
  },
  "RB12": {
    "jp": "ブラックナイト",
    "en": "Blacknight",
    "ch": "夜半"
  },
  "RF02": {
    "jp": "寒芒クルース",
    "en": "Kroos K.G.",
    "ch": "寒芒克洛丝"
  },
  "R121": {
    "jp": "クエルクス",
    "en": "Quercus",
    "ch": "夏栎"
  },
  "LT10": {
    "jp": "エンフォーサー",
    "en": "Enforcer",
    "ch": "见行者"
  },
  "HK09": {
    "jp": "カゼマル",
    "en": "Kazemaru",
    "ch": "风丸"
  },
  "VC18": {
    "jp": "ロックロック",
    "en": "Rockrock",
    "ch": "洛洛"
  },
  "VC19": {
    "jp": "ハイディ",
    "en": "Heidi",
    "ch": "海蒂"
  },
  "CB19": {
    "jp": "ウィンドフリット",
    "en": "Windflit",
    "ch": "掠风"
  },
  "MN07": {
    "jp": "エラト",
    "en": "Erato",
    "ch": "埃拉托"
  },
  "LN06": {
    "jp": "ツェルニー",
    "en": "Czerny",
    "ch": "车尔尼"
  },
  "RF03": {
    "jp": "濯塵ハイビスカス",
    "en": "Hibiscus P.F.",
    "ch": "濯尘芙蓉"
  },
  "RL08": {
    "jp": "アステジーニ",
    "en": "Astgenne",
    "ch": "星源"
  },
  "RF23": {
    "jp": "承曦グレイ",
    "en": "Greyy L.B.",
    "ch": "承曦格雷伊"
  },
  "R143": {
    "jp": "カンタービレ",
    "en": "Cantabile",
    "ch": "晓歌"
  },
  "SG09": {
    "jp": "ミニマリスト",
    "en": "Minimalist",
    "ch": "至简"
  },
  "KZ10": {
    "jp": "プロヴァイゾ",
    "en": "Proviso",
    "ch": "但书"
  },
  "II10": {
    "jp": "ハイモア",
    "en": "Highmore",
    "ch": "海沫"
  },
  "R175": {
    "jp": "パプリカ",
    "en": "Paprika",
    "ch": "明椒"
  },
  "GG04": {
    "jp": "ダグザ",
    "en": "Dagda",
    "ch": "达格达"
  },
  "SR37": {
    "jp": "ルナカブ",
    "en": "Lunacub",
    "ch": "子月"
  },
  "SI03": {
    "jp": "カニパラート",
    "en": "Qanipalaat",
    "ch": "雪绒"
  },
  "DB03": {
    "jp": "ハーモニー",
    "en": "Harmonie",
    "ch": "和弦"
  },
  "VC21": {
    "jp": "パズル",
    "en": "Pazzle",
    "ch": "谜图"
  },
  "RB09": {
    "jp": "ファイヤーホイッスル",
    "en": "Firewhistle",
    "ch": "火哨"
  },
  "YD15": {
    "jp": "ジエユン",
    "en": "Jieyun",
    "ch": "截云"
  },
  "YD17": {
    "jp": "ウィンドチャイム",
    "en": "Wind Chimes",
    "ch": "铎铃"
  },
  "MH03": {
    "jp": "レウスSノイルホーン",
    "en": "Noir Corne R.S",
    "ch": "火龙S黑角"
  },
  "RB11": {
    "jp": "セメント",
    "en": "Cement",
    "ch": "洋灰"
  },
  "GG02": {
    "jp": "モーガン",
    "en": "Morgan",
    "ch": "摩根"
  },
  "CB22": {
    "jp": "メラナイト",
    "en": "Melanite",
    "ch": "玫拉"
  },
  "LT12": {
    "jp": "スプリア",
    "en": "Spuria",
    "ch": "空构"
  },
  "LT13": {
    "jp": "インサイダー",
    "en": "Insider",
    "ch": "隐现"
  },
  "SI02": {
    "jp": "サンタラ",
    "en": "Santalla",
    "ch": "寒檀"
  },
  "SI06": {
    "jp": "ヴァラルクビン",
    "en": "Valarqvin",
    "ch": "凛视"
  },
  "SS04": {
    "jp": "ポンシラス",
    "en": "Poncirus",
    "ch": "青枳"
  },
  "SS03": {
    "jp": "ブライオファイタ",
    "en": "Bryophyta",
    "ch": "苍苔"
  },
  "BS05": {
    "jp": "アーモンド",
    "en": "Almond",
    "ch": "杏仁"
  },
  "CB28": {
    "jp": "コールドショット",
    "en": "Coldshot",
    "ch": "冰酿"
  },
  "VC23": {
    "jp": "ヴァンデラ",
    "en": "Vendela",
    "ch": "刺玫"
  },
  "VC24": {
    "jp": "デルフィーン",
    "en": "Delphine",
    "ch": "戴菲恩"
  },
  "LN21": {
    "jp": "ディアマンテ",
    "en": "Diamante",
    "ch": "折光"
  },
  "LN13": {
    "jp": "ベースライン",
    "en": "Bassline",
    "ch": "深律"
  },
  "USS5": {
    "jp": "リェータ",
    "en": "Лето",
    "ch": "烈夏"
  },
  "VC27": {
    "jp": "ハロルド",
    "en": "Harold",
    "ch": "哈洛德"
  },
  "RB14": {
    "jp": "ウォーミー",
    "en": "Warmy",
    "ch": "温米"
  },
  "YD13": {
    "jp": "ワンチィン",
    "en": "Wanqing",
    "ch": "万顷"
  },
  "YD14": {
    "jp": "グレインバッズ",
    "en": "Grainbuds",
    "ch": "小满"
  },
  "SG12": {
    "jp": "ケストレル",
    "en": "Kestrel",
    "ch": "红隼"
  },
  "RS06": {
    "jp": "Doc",
    "en": "Doc",
    "ch": "医生"
  },
  "RS07": {
    "jp": "Iana",
    "en": "Iana",
    "ch": "双月"
  },
  "RS08": {
    "jp": "Fuze",
    "en": "Fuze",
    "ch": "导火索"
  },
  "SR39": {
    "jp": "アロマ",
    "en": "Aroma",
    "ch": "阿罗玛"
  },
  "R167": {
    "jp": "オッダ",
    "en": "Odda",
    "ch": "奥达"
  },
  "RF04": {
    "jp": "歴陣鋭槍フェン",
    "en": "Fang F.S.",
    "ch": "历阵锐枪芬"
  },
  "AE03": {
    "jp": "アンダーフロー",
    "en": "Underflow",
    "ch": "深巡"
  },
  "AE05": {
    "jp": "ルシーラ",
    "en": "Lucilla",
    "ch": "海霓"
  },
  "R184": {
    "jp": "ミトム",
    "en": "Mitm",
    "ch": "渡桥"
  },
  "CB30": {
    "jp": "ブリキ",
    "en": "Tin Man",
    "ch": "锡人"
  },
  "SG23": {
    "jp": "サンドレコナー",
    "en": "Sandreckoner",
    "ch": "衡沙"
  },
  "SG19": {
    "jp": "パピルス",
    "en": "Papyrus",
    "ch": "莎草"
  },
  "DD01": {
    "jp": "ライオス",
    "en": "Laios",
    "ch": "莱欧斯"
  },
  "DD03": {
    "jp": "チルチャック",
    "en": "Chilchuck",
    "ch": "齐尔查克"
  },
  "DD04": {
    "jp": "センシ",
    "en": "Senshi",
    "ch": "森西"
  },
  "VC20": {
    "jp": "キャサリン",
    "en": "Catherine",
    "ch": "凯瑟琳"
  },
  "CB32": {
    "jp": "ボビン",
    "en": "Bobbing",
    "ch": "波卜"
  },
  "SR41": {
    "jp": "フィグリーノ",
    "en": "Figurino",
    "ch": "裁度"
  },
  "SG10": {
    "jp": "フィラエ",
    "en": "Philae",
    "ch": "菲莱"
  },
  "BV23": {
    "jp": "テクノ",
    "en": "Tecno",
    "ch": "特克诺"
  },
  "II11": {
    "jp": "ローズソルト",
    "en": "Rose Salt",
    "ch": "瑰盐"
  },
  "YD18": {
    "jp": "シンジュウ",
    "en": "Xingzhu",
    "ch": "行箸"
  },
  "BS07": {
    "jp": "サーファー",
    "en": "Surfer",
    "ch": "寻澜"
  },
  "VC29": {
    "jp": "ノウエル",
    "en": "Nowell",
    "ch": "诺威尔"
  },
  "JC04": {
    "jp": "クーリエ",
    "en": "Courier",
    "ch": "讯使"
  },
  "SW02": {
    "jp": "スカベンジャー",
    "en": "Scavenger",
    "ch": "清道夫"
  },
  "R105": {
    "jp": "ヴィグナ",
    "en": "Vigna",
    "ch": "红豆"
  },
  "R104": {
    "jp": "ミルラ",
    "en": "Myrrh",
    "ch": "末药"
  },
  "IU07": {
    "jp": "ガヴィル",
    "en": "Gavial",
    "ch": "嘉维尔"
  },
  "MN03": {
    "jp": "パフューマー",
    "en": "Perfumer",
    "ch": "调香师"
  },
  "VC02": {
    "jp": "ヘイズ",
    "en": "Haze",
    "ch": "夜烟"
  },
  "SI01": {
    "jp": "ギターノ",
    "en": "Gitano",
    "ch": "远山"
  },
  "KZ04": {
    "jp": "グラベル",
    "en": "Gravel",
    "ch": "砾"
  },
  "RB02": {
    "jp": "ロープ",
    "en": "Rope",
    "ch": "暗索"
  },
  "LM11": {
    "jp": "ショウ",
    "en": "Shaw",
    "ch": "阿消"
  },
  "LM10": {
    "jp": "シラユキ",
    "en": "ShiraYuki",
    "ch": "白雪"
  },
  "ST02": {
    "jp": "メテオ",
    "en": "Meteor",
    "ch": "流星"
  },
  "BS03": {
    "jp": "ジェシカ",
    "en": "Jessica",
    "ch": "杰西卡"
  },
  "AA04": {
    "jp": "ディピカ",
    "en": "Deepcolor",
    "ch": "深海色"
  },
  "LN01": {
    "jp": "アーススピリット",
    "en": "Earthspirit",
    "ch": "地灵"
  },
  "R100": {
    "jp": "ドーベルマン",
    "en": "Dobermann",
    "ch": "杜宾"
  },
  "IU04": {
    "jp": "エステル",
    "en": "Estelle",
    "ch": "艾丝黛尔"
  },
  "US10": {
    "jp": "ビーハンター",
    "en": "Beehunter",
    "ch": "猎蜂"
  },
  "VC04": {
    "jp": "ムース",
    "en": "Mousse",
    "ch": "慕斯"
  },
  "R123": {
    "jp": "フロストリーフ",
    "en": "Frostleaf",
    "ch": "霜叶"
  },
  "HK01": {
    "jp": "マトイマル",
    "en": "Matoimaru",
    "ch": "缠丸"
  },
  "IU05": {
    "jp": "クオーラ",
    "en": "Cuora",
    "ch": "蛇屠箱"
  },
  "USS3": {
    "jp": "グム",
    "en": "Gummy",
    "ch": "古米"
  },
  "JC03": {
    "jp": "マッターホルン",
    "en": "Matterhorn",
    "ch": "角峰"
  },
  "R119": {
    "jp": "グレイ",
    "en": "Greyy",
    "ch": "格雷伊"
  },
  "R107": {
    "jp": "ススーロ",
    "en": "Sussurro",
    "ch": "苏苏洛"
  },
  "R108": {
    "jp": "テンニンカ",
    "en": "Myrtle",
    "ch": "桃金娘"
  },
  "R124": {
    "jp": "ジュナー",
    "en": "Dur-nar",
    "ch": "坚雷"
  },
  "R122": {
    "jp": "ヴァーミル",
    "en": "Vermeil",
    "ch": "红云"
  },
  "R130": {
    "jp": "イーサン",
    "en": "Ethan",
    "ch": "伊桑"
  },
  "VC01": {
    "jp": "メイ",
    "en": "May",
    "ch": "梅"
  },
  "LT02": {
    "jp": "アンブリエル",
    "en": "Ambriel",
    "ch": "安比尔"
  },
  "R160": {
    "jp": "セイリュウ",
    "en": "Purestream",
    "ch": "清流"
  },
  "HK03": {
    "jp": "ウタゲ",
    "en": "Utage",
    "ch": "宴"
  },
  "MN01": {
    "jp": "コンビクション",
    "en": "Conviction",
    "ch": "断罪者"
  },
  "R144": {
    "jp": "カッター",
    "en": "Cutter",
    "ch": "刻刀"
  },
  "R157": {
    "jp": "ポデンコ",
    "en": "Podenco",
    "ch": "波登可"
  },
  "R140": {
    "jp": "カシャ",
    "en": "Click",
    "ch": "卡达"
  },
  "LM14": {
    "jp": "ジェイ",
    "en": "Jaye",
    "ch": "孑"
  },
  "R139": {
    "jp": "アシッドドロップ",
    "en": "Aciddrop",
    "ch": "酸糖"
  },
  "LT06": {
    "jp": "アレーン",
    "en": "Arene",
    "ch": "芳汀"
  },
  "R146": {
    "jp": "バブル",
    "en": "Bubble",
    "ch": "泡泡"
  },
  "R166": {
    "jp": "ジャッキー",
    "en": "Jackie",
    "ch": "杰克"
  },
  "CB09": {
    "jp": "パインコーン",
    "en": "Pinecone",
    "ch": "松果"
  },
  "CB16": {
    "jp": "ビーンストーク",
    "en": "Beanstalk",
    "ch": "豆苗"
  },
  "II05": {
    "jp": "インディゴ",
    "en": "Indigo",
    "ch": "深靛"
  },
  "CB11": {
    "jp": "ロベルタ",
    "en": "Roberta",
    "ch": "罗比菈塔"
  },
  "CB03": {
    "jp": "プリン",
    "en": "Pudding",
    "ch": "布丁"
  },
  "R134": {
    "jp": "チェストナット",
    "en": "Chestnut",
    "ch": "褐果"
  },
  "R161": {
    "jp": "羅小黒",
    "en": "Luo Xiaiohei",
    "ch": "罗小黑"
  },
  "SG11": {
    "jp": "トター",
    "en": "Totter",
    "ch": "铅踝"
  },
  "CB18": {
    "jp": "クォーツ",
    "en": "Quartz",
    "ch": "石英"
  },
  "R171": {
    "jp": "ヒューマス",
    "en": "Humus",
    "ch": "休谟斯"
  },
  "VC25": {
    "jp": "ヴァーダント",
    "en": "Verdant",
    "ch": "维荻"
  },
  "BV32": {
    "jp": "ケイパー",
    "en": "Caper",
    "ch": "跃跃"
  },
  "BV33": {
    "jp": "ルトナダ",
    "en": "Lutonada",
    "ch": "露托"
  },
  "CB33": {
    "jp": "コントレイル",
    "en": "Contrail",
    "ch": "云迹"
  },
  "PA11": {
    "jp": "フェン",
    "en": "Fang",
    "ch": "芬"
  },
  "BS04": {
    "jp": "バニラ",
    "en": "Vanilla",
    "ch": "香草"
  },
  "LT05": {
    "jp": "プリュム",
    "en": "Plume",
    "ch": "翎羽"
  },
  "PA13": {
    "jp": "ハイビスカス",
    "en": "Hibiscus",
    "ch": "芙蓉"
  },
  "PA43": {
    "jp": "アンセル",
    "en": "Ansel",
    "ch": "安赛尔"
  },
  "PA15": {
    "jp": "ラヴァ",
    "en": "Lava",
    "ch": "炎熔"
  },
  "PA42": {
    "jp": "スチュワード",
    "en": "Steward",
    "ch": "史都华德"
  },
  "PA12": {
    "jp": "クルース",
    "en": "Kroos",
    "ch": "克洛丝"
  },
  "PA44": {
    "jp": "アドナキエル",
    "en": "Adnachiel",
    "ch": "安德切尔"
  },
  "PA61": {
    "jp": "オーキッド",
    "en": "Orchid",
    "ch": "梓兰"
  },
  "PA41": {
    "jp": "メランサ",
    "en": "Melantha",
    "ch": "玫兰莎"
  },
  "PA14": {
    "jp": "ビーグル",
    "en": "Beagle",
    "ch": "米格鲁"
  },
  "PA45": {
    "jp": "カーディ",
    "en": "Cardigan",
    "ch": "卡缇"
  },
  "PA63": {
    "jp": "カタパルト",
    "en": "Catapult",
    "ch": "空爆"
  },
  "PA62": {
    "jp": "ミッドナイト",
    "en": "Midnight",
    "ch": "月见夜"
  },
  "PA65": {
    "jp": "ポプカル",
    "en": "Popukar",
    "ch": "泡普卡"
  },
  "PA64": {
    "jp": "スポット",
    "en": "Spot",
    "ch": "斑点"
  },
  "A41": {
    "jp": "ヤトウ",
    "en": "Yato",
    "ch": "夜刀"
  },
  "A44": {
    "jp": "ドゥリン",
    "en": "Durin",
    "ch": "杜林"
  },
  "R303": {
    "jp": "12F",
    "en": "12F",
    "ch": "12F"
  },
  "A42": {
    "jp": "レンジャー",
    "en": "Rangers",
    "ch": "巡林者"
  },
  "A43": {
    "jp": "ノイルホーン",
    "en": "Noir Corne",
    "ch": "黑角"
  },
  "RCX2": {
    "jp": "Lancet-2",
    "en": "Lancet-2",
    "ch": "Lancet-2"
  },
  "RCX3": {
    "jp": "Castle-3",
    "en": "Castle-3",
    "ch": "Castle-3"
  },
  "RCX4": {
    "jp": "Thermal-EX",
    "en": "Thermal-EX",
    "ch": "Thermal-EX"
  },
  "KZ15": {
    "jp": "Justice Knight",
    "en": "Justice Knight",
    "ch": "正义骑士号"
  },
  "MH01": {
    "jp": "テラ大陸調査団",
    "en": "Terra Research Commission",
    "ch": "泰拉大陆调查团"
  },
  "U007": {
    "jp": "U-Official",
    "en": "U-Official",
    "ch": "U-Official"
  },
  "RCX5": {
    "jp": "Friston-3",
    "en": "Friston-3",
    "ch": "Friston-3"
  },
  "RCX6": {
    "jp": "PhonoR-0",
    "en": "PhonoR-0",
    "ch": "PhonoR-0"
  },
  "[Material]": {
    "jp": "",
    "en": "",
    "ch": ""
  }
}